databricks_zerobus_ingest_sdk-0.2.0.dist-info/licenses/LICENSE
databricks_zerobus_ingest_sdk-0.2.0.dist-info/licenses/NOTICE
zerobus/__init__.py
zerobus/sdk/__init__.py
zerobus/sdk/aio/__init__.py
zerobus/sdk/aio/zerobus_sdk.py
zerobus/sdk/shared/__init__.py
zerobus/sdk/shared/definitions.py
zerobus/sdk/shared/headers_provider.py
zerobus/sdk/shared/zerobus_service_pb2.py
zerobus/sdk/shared/zerobus_service_pb2.pyi
zerobus/sdk/shared/zerobus_service_pb2_grpc.py
zerobus/sdk/sync/__init__.py
zerobus/sdk/sync/zerobus_sdk.py
zerobus/tools/generate_proto.py
databricks_zerobus_ingest_sdk-0.2.0.dist-info/METADATA
databricks_zerobus_ingest_sdk-0.2.0.dist-info/WHEEL
databricks_zerobus_ingest_sdk-0.2.0.dist-info/top_level.txt
databricks_zerobus_ingest_sdk-0.2.0.dist-info/RECORD
