Metadata-Version: 2.4
Name: databricks-zerobus-ingest-sdk
Version: 0.2.0
Summary: Databricks Zerobus Ingest SDK for Python
License: LicenseRef-Proprietary
Keywords: zerobus,databricks,sdk
Classifier: Development Status :: 5 - Production/Stable
Classifier: Intended Audience :: Developers
Classifier: Intended Audience :: Science/Research
Classifier: Intended Audience :: System Administrators
Classifier: Programming Language :: Python :: 3.9
Classifier: Programming Language :: Python :: 3.10
Classifier: Programming Language :: Python :: 3.11
Classifier: Programming Language :: Python :: 3.12
Classifier: Programming Language :: Python :: 3.13
Classifier: Operating System :: OS Independent
Requires-Python: >=3.9
License-File: LICENSE
License-File: NOTICE
Requires-Dist: requests<3,>=2.28.1
Requires-Dist: grpcio<2.0,>=1.60.0
Requires-Dist: protobuf<7.0,>=4.25.0
Provides-Extra: dev
Requires-Dist: wheel; extra == "dev"
Requires-Dist: build; extra == "dev"
Requires-Dist: grpcio-tools<2.0,>=1.60.0; extra == "dev"
Requires-Dist: black; extra == "dev"
Requires-Dist: pycodestyle; extra == "dev"
Requires-Dist: autoflake; extra == "dev"
Requires-Dist: isort; extra == "dev"
Requires-Dist: pytest; extra == "dev"
Requires-Dist: pytest-cov; extra == "dev"
Requires-Dist: pytest-xdist<4.0,>=3.6.1; extra == "dev"
Requires-Dist: pytest-asyncio; extra == "dev"
Dynamic: license-file
